kaniko_remote/__init__.py
kaniko_remote/_version.py
kaniko_remote/authorisers.py
kaniko_remote/builder.py
kaniko_remote/config.py
kaniko_remote/k8s.py
kaniko_remote/k8s_specs.py
kaniko_remote/logging.py
kaniko_remote/main.py
kaniko_remote/tagger.py
kaniko_remote-0.6.1.dist-info/LICENSE
kaniko_remote-0.6.1.dist-info/METADATA
kaniko_remote-0.6.1.dist-info/WHEEL
kaniko_remote-0.6.1.dist-info/entry_points.txt
kaniko_remote-0.6.1.dist-info/top_level.txt
kaniko_remote-0.6.1.dist-info/RECORD
