Metadata-Version: 2.1
Name: kaniko-remote
Version: 0.6.1
Summary: Enable familiar `docker build` semantics using kaniko on k8s
Author: Lucas
Author-email: me@lucas.fish
License: MIT License
Project-URL: github, https://github.com/JJ11teen/kaniko-remote
Project-URL: pypi, https://pypi.org/project/kaniko-remote
Keywords: kaniko,kubernetes,k8s,docker,build,images,remote
Platform: UNKNOWN
Classifier: Programming Language :: Python :: 3
Classifier: License :: OSI Approved :: MIT License
Classifier: Operating System :: OS Independent
License-File: LICENSE
Requires-Dist: asyncclick (>=8.0)
Requires-Dist: anyio (>=3.5)
Requires-Dist: ruamel.yaml (>=0.3)
Requires-Dist: tqdm (>=4)
Requires-Dist: kubernetes (>=22.6)
Requires-Dist: deflatable-dict
Requires-Dist: pathspec (>=0.9)
Provides-Extra: docker
Requires-Dist: kaniko-remote-docker-cli ; extra == 'docker'
Provides-Extra: tests
Requires-Dist: pytest (==6.2.4) ; extra == 'tests'
